{
  "": "",
  "Articles App": "Articles App",
  "Car": "Car",
  "IT": "IT",
  "choose value": "",
  "Аватар": "Аватар",
  "Авторизация": "",
  "Валюта": "Валюта",
  "Ваша фамилия": "Ваша фамилия",
  "Ваше имя": "Ваше имя",
  "Введите комментарий": "Введите комментарий",
  "Возраст": "Возраст",
  "Войти": "",
  "Все": "Все",
  "Все статьи": "Все статьи",
  "Выберите валюту": "",
  "Выйти": "",
  "Выкинуть ошибку": "Выкинуть ошибку",
  "Главная": "Главная",
  "Город": "Город",
  "Добавить статью": "Добавить статью",
  "Имя и фамилия обязательны": "Имя и фамилия обязательны",
  "Категория": "Категория",
  "Комментарии": "Комментарии",
  "Логин": "Логин",
  "Назад": "Назад",
  "Наука": "Наука",
  "Не данных": "Не данных",
  "Некорректный возраст": "Некорректный возраст",
  "Нет данных": "Нет данных",
  "Нет комментариев": "Нет комментариев",
  "О нас": "О нас",
  "О сайте": "О сайте",
  "Обновить страницу": "Обновить страницу",
  "Отменить": "Отменить",
  "Отправить": "Отправить",
  "Ошибка": "Ошибка",
  "Ошибка при загрузке статей": "Ошибка при загрузке статей",
  "Ошибка сервера": "Ошибка сервера",
  "Пароль": "Пароль",
  "Переключить": "",
  "По возрастанию": "По возрастанию",
  "По дате создания": "По дате создания",
  "По количеству просмотров": "По количеству просмотров",
  "По названию": "По названию",
  "По убыванию": "По убыванию",
  "Поиск": "Поиск",
  "Пользователь не найден или Вы ввели неверный логиг или пароль": "",
  "Порядок": "Порядок",
  "Произошла ошибка при загрузке статьи": "Произошла ошибка при загрузке статьи",
  "Профиль": "Профиль",
  "Профиль пользователя": "Профиль пользователя",
  "Профиль1": "Профиль1",
  "Профиль123": "Профиль123",
  "Профиль2": "Профиль2",
  "Редактирование статьи с ID = ": "Редактирование статьи с ID = ",
  "Редактировать": "Редактировать",
  "Рекомендуем": "Рекомендуем",
  "Создание новой статьи": "Создание новой статьи",
  "Сортировка": "Сортировка",
  "Сохранить": "Сохранить",
  "Статья не найдена": "Статья не найдена",
  "Страна": "Страна",
  "Страна обязательна": "Страна обязательна",
  "Страница не найдена": "Страница не найдена",
  "Текущий Язык": "Текущий Язык",
  "Хуй": "Хуй",
  "Читать далее": {
    "": {
      "": {
        "": ""
      }
    }
  },
  "Что-то пошло не так": "Что-то пошло не так",
  "Экономика": "Экономика"
}
